Metadata-Version: 2.1
Name: django-error-report-2
Version: 0.4.2
Summary: View Django Error Report in Django Admin
Home-page: https://github.com/matmair/django-error-report-2
Author: M Hassan Siddiqui
Author-email: mhassan.eeng@gmail.com
License: BSD License
Classifier: Environment :: Web Environment
Classifier: Intended Audience :: Developers
Classifier: License :: OSI Approved :: BSD License
Classifier: Operating System :: OS Independent
Classifier: Programming Language :: Python
Classifier: Framework :: Django
License-File: LICENSE.txt
Requires-Dist: Django >=1.7
